setup.py
egcarren_dist/Binomialdistribution.py
egcarren_dist/Gaussiandistribution.py
egcarren_dist/Generaldistribution.py
egcarren_dist/__init__.py
egcarren_dist.egg-info/PKG-INFO
egcarren_dist.egg-info/SOURCES.txt
egcarren_dist.egg-info/dependency_links.txt
egcarren_dist.egg-info/not-zip-safe
egcarren_dist.egg-info/top_level.txt